atlaversity/__init__.py
atlaversity/__main__.py
atlaversity/editor/CommandLine.py
atlaversity/editor/MageTable.py
atlaversity/editor/OrderEditor.css
atlaversity/editor/OrderEditor.py
atlaversity/editor/Prompt.py
atlaversity/editor/StudyTable.py
atlaversity/editor/ValueInput.py
atlaversity/editor/ValueSelector.py
atlaversity/game/Game.py
atlaversity/game/Mage.py
atlaversity/game/Skill.py
atlaversity/game/SkillLevel.py
atlaversity/game/Turn.py
atlaversity/utils/Config.py
atlaversity/utils/Logging.py
atlaversity-0.1.1.dist-info/METADATA
atlaversity-0.1.1.dist-info/WHEEL
atlaversity-0.1.1.dist-info/licenses/LICENSE
atlaversity-0.1.1.dist-info/RECORD
