Metadata-Version: 2.3
Name: atlaversity
Version: 0.1.1
Summary: Study aid for Atlantis PBEM game.
Project-URL: bugs, https://github.com/rmstdope/atlaversity/issues
Project-URL: homepage, https://github.com/rmstdope/atlaversity
Author-email: Henrik Kurelid <henrik@kurelid.se>
Maintainer-email: Henrik Kurelid <henrik@kurelid.se>
License: MIT License
Classifier: Development Status :: 4 - Beta
Classifier: Programming Language :: Python :: 3
Requires-Python: >=3.8
Requires-Dist: prompt-toolkit==3.0.48
Requires-Dist: textual==0.82.0
Provides-Extra: dev
Requires-Dist: pytest; extra == 'dev'
